{"nodes": [{"id": "e_livekit_creativenest_admin_panel_frontend_assets_scripts_agent_edit_js", "label": "agent-edit.js", "file_type": "code", "source_file": "E:\\Livekit-CreativeNest\\Admin-Panel\\frontend\\assets\\scripts\\agent-edit.js", "source_location": "L1"}, {"id": "agent_edit_setupagentediteventlisteners", "label": "setupAgentEditEventListeners()", "file_type": "code", "source_file": "E:\\Livekit-CreativeNest\\Admin-Panel\\frontend\\assets\\scripts\\agent-edit.js", "source_location": "L17"}, {"id": "agent_edit_loadagentdetail", "label": "loadAgentDetail()", "file_type": "code", "source_file": "E:\\Livekit-CreativeNest\\Admin-Panel\\frontend\\assets\\scripts\\agent-edit.js", "source_location": "L64"}, {"id": "agent_edit_populateagentform", "label": "populateAgentForm()", "file_type": "code", "source_file": "E:\\Livekit-CreativeNest\\Admin-Panel\\frontend\\assets\\scripts\\agent-edit.js", "source_location": "L131"}, {"id": "agent_edit_handleagentformsubmit", "label": "handleAgentFormSubmit()", "file_type": "code", "source_file": "E:\\Livekit-CreativeNest\\Admin-Panel\\frontend\\assets\\scripts\\agent-edit.js", "source_location": "L205"}, {"id": "agent_edit_handleagentdelete", "label": "handleAgentDelete()", "file_type": "code", "source_file": "E:\\Livekit-CreativeNest\\Admin-Panel\\frontend\\assets\\scripts\\agent-edit.js", "source_location": "L343"}, {"id": "agent_edit_rendertoolsselector", "label": "renderToolsSelector()", "file_type": "code", "source_file": "E:\\Livekit-CreativeNest\\Admin-Panel\\frontend\\assets\\scripts\\agent-edit.js", "source_location": "L372"}, {"id": "agent_edit_toggletoolsdropdown", "label": "toggleToolsDropdown()", "file_type": "code", "source_file": "E:\\Livekit-CreativeNest\\Admin-Panel\\frontend\\assets\\scripts\\agent-edit.js", "source_location": "L430"}, {"id": "agent_edit_updatetoolsdropdownsummary", "label": "updateToolsDropdownSummary()", "file_type": "code", "source_file": "E:\\Livekit-CreativeNest\\Admin-Panel\\frontend\\assets\\scripts\\agent-edit.js", "source_location": "L443"}, {"id": "agent_edit_getagentidfromurl", "label": "getAgentIdFromUrl()", "file_type": "code", "source_file": "E:\\Livekit-CreativeNest\\Admin-Panel\\frontend\\assets\\scripts\\agent-edit.js", "source_location": "L470"}, {"id": "agent_edit_populatettsprovideroptions", "label": "populateTtsProviderOptions()", "file_type": "code", "source_file": "E:\\Livekit-CreativeNest\\Admin-Panel\\frontend\\assets\\scripts\\agent-edit.js", "source_location": "L475"}, {"id": "agent_edit_populatettsvoiceoptions", "label": "populateTtsVoiceOptions()", "file_type": "code", "source_file": "E:\\Livekit-CreativeNest\\Admin-Panel\\frontend\\assets\\scripts\\agent-edit.js", "source_location": "L495"}], "edges": [{"source": "e_livekit_creativenest_admin_panel_frontend_assets_scripts_agent_edit_js", "target": "agent_edit_setupagentediteventlisteners", "relation": "contains", "confidence": "EXTRACTED", "source_file": "E:\\Livekit-CreativeNest\\Admin-Panel\\frontend\\assets\\scripts\\agent-edit.js", "source_location": "L17", "weight": 1.0}, {"source": "e_livekit_creativenest_admin_panel_frontend_assets_scripts_agent_edit_js", "target": "agent_edit_loadagentdetail", "relation": "contains", "confidence": "EXTRACTED", "source_file": "E:\\Livekit-CreativeNest\\Admin-Panel\\frontend\\assets\\scripts\\agent-edit.js", "source_location": "L64", "weight": 1.0}, {"source": "e_livekit_creativenest_admin_panel_frontend_assets_scripts_agent_edit_js", "target": "agent_edit_populateagentform", "relation": "contains", "confidence": "EXTRACTED", "source_file": "E:\\Livekit-CreativeNest\\Admin-Panel\\frontend\\assets\\scripts\\agent-edit.js", "source_location": "L131", "weight": 1.0}, {"source": "e_livekit_creativenest_admin_panel_frontend_assets_scripts_agent_edit_js", "target": "agent_edit_handleagentformsubmit", "relation": "contains", "confidence": "EXTRACTED", "source_file": "E:\\Livekit-CreativeNest\\Admin-Panel\\frontend\\assets\\scripts\\agent-edit.js", "source_location": "L205", "weight": 1.0}, {"source": "e_livekit_creativenest_admin_panel_frontend_assets_scripts_agent_edit_js", "target": "agent_edit_handleagentdelete", "relation": "contains", "confidence": "EXTRACTED", "source_file": "E:\\Livekit-CreativeNest\\Admin-Panel\\frontend\\assets\\scripts\\agent-edit.js", "source_location": "L343", "weight": 1.0}, {"source": "e_livekit_creativenest_admin_panel_frontend_assets_scripts_agent_edit_js", "target": "agent_edit_rendertoolsselector", "relation": "contains", "confidence": "EXTRACTED", "source_file": "E:\\Livekit-CreativeNest\\Admin-Panel\\frontend\\assets\\scripts\\agent-edit.js", "source_location": "L372", "weight": 1.0}, {"source": "e_livekit_creativenest_admin_panel_frontend_assets_scripts_agent_edit_js", "target": "agent_edit_toggletoolsdropdown", "relation": "contains", "confidence": "EXTRACTED", "source_file": "E:\\Livekit-CreativeNest\\Admin-Panel\\frontend\\assets\\scripts\\agent-edit.js", "source_location": "L430", "weight": 1.0}, {"source": "e_livekit_creativenest_admin_panel_frontend_assets_scripts_agent_edit_js", "target": "agent_edit_updatetoolsdropdownsummary", "relation": "contains", "confidence": "EXTRACTED", "source_file": "E:\\Livekit-CreativeNest\\Admin-Panel\\frontend\\assets\\scripts\\agent-edit.js", "source_location": "L443", "weight": 1.0}, {"source": "e_livekit_creativenest_admin_panel_frontend_assets_scripts_agent_edit_js", "target": "agent_edit_getagentidfromurl", "relation": "contains", "confidence": "EXTRACTED", "source_file": "E:\\Livekit-CreativeNest\\Admin-Panel\\frontend\\assets\\scripts\\agent-edit.js", "source_location": "L470", "weight": 1.0}, {"source": "e_livekit_creativenest_admin_panel_frontend_assets_scripts_agent_edit_js", "target": "agent_edit_populatettsprovideroptions", "relation": "contains", "confidence": "EXTRACTED", "source_file": "E:\\Livekit-CreativeNest\\Admin-Panel\\frontend\\assets\\scripts\\agent-edit.js", "source_location": "L475", "weight": 1.0}, {"source": "e_livekit_creativenest_admin_panel_frontend_assets_scripts_agent_edit_js", "target": "agent_edit_populatettsvoiceoptions", "relation": "contains", "confidence": "EXTRACTED", "source_file": "E:\\Livekit-CreativeNest\\Admin-Panel\\frontend\\assets\\scripts\\agent-edit.js", "source_location": "L495", "weight": 1.0}, {"source": "agent_edit_loadagentdetail", "target": "agent_edit_populatettsprovideroptions", "relation": "calls", "confidence": "EXTRACTED", "source_file": "E:\\Livekit-CreativeNest\\Admin-Panel\\frontend\\assets\\scripts\\agent-edit.js", "source_location": "L88", "weight": 1.0}, {"source": "agent_edit_loadagentdetail", "target": "agent_edit_getagentidfromurl", "relation": "calls", "confidence": "EXTRACTED", "source_file": "E:\\Livekit-CreativeNest\\Admin-Panel\\frontend\\assets\\scripts\\agent-edit.js", "source_location": "L98", "weight": 1.0}, {"source": "agent_edit_loadagentdetail", "target": "agent_edit_rendertoolsselector", "relation": "calls", "confidence": "EXTRACTED", "source_file": "E:\\Livekit-CreativeNest\\Admin-Panel\\frontend\\assets\\scripts\\agent-edit.js", "source_location": "L105", "weight": 1.0}, {"source": "agent_edit_loadagentdetail", "target": "agent_edit_populateagentform", "relation": "calls", "confidence": "EXTRACTED", "source_file": "E:\\Livekit-CreativeNest\\Admin-Panel\\frontend\\assets\\scripts\\agent-edit.js", "source_location": "L112", "weight": 1.0}, {"source": "agent_edit_populateagentform", "target": "agent_edit_populatettsvoiceoptions", "relation": "calls", "confidence": "EXTRACTED", "source_file": "E:\\Livekit-CreativeNest\\Admin-Panel\\frontend\\assets\\scripts\\agent-edit.js", "source_location": "L161", "weight": 1.0}, {"source": "agent_edit_populateagentform", "target": "agent_edit_rendertoolsselector", "relation": "calls", "confidence": "EXTRACTED", "source_file": "E:\\Livekit-CreativeNest\\Admin-Panel\\frontend\\assets\\scripts\\agent-edit.js", "source_location": "L202", "weight": 1.0}, {"source": "agent_edit_rendertoolsselector", "target": "agent_edit_updatetoolsdropdownsummary", "relation": "calls", "confidence": "EXTRACTED", "source_file": "E:\\Livekit-CreativeNest\\Admin-Panel\\frontend\\assets\\scripts\\agent-edit.js", "source_location": "L427", "weight": 1.0}], "raw_calls": [{"caller_nid": "agent_edit_setupagentediteventlisteners", "callee": "getElementById", "source_file": "E:\\Livekit-CreativeNest\\Admin-Panel\\frontend\\assets\\scripts\\agent-edit.js", "source_location": "L18"}, {"caller_nid": "agent_edit_setupagentediteventlisteners", "callee": "addEventListener", "source_file": "E:\\Livekit-CreativeNest\\Admin-Panel\\frontend\\assets\\scripts\\agent-edit.js", "source_location": "L20"}, {"caller_nid": "agent_edit_setupagentediteventlisteners", "callee": "getElementById", "source_file": "E:\\Livekit-CreativeNest\\Admin-Panel\\frontend\\assets\\scripts\\agent-edit.js", "source_location": "L23"}, {"caller_nid": "agent_edit_setupagentediteventlisteners", "callee": "addEventListener", "source_file": "E:\\Livekit-CreativeNest\\Admin-Panel\\frontend\\assets\\scripts\\agent-edit.js", "source_location": "L25"}, {"caller_nid": "agent_edit_setupagentediteventlisteners", "callee": "getElementById", "source_file": "E:\\Livekit-CreativeNest\\Admin-Panel\\frontend\\assets\\scripts\\agent-edit.js", "source_location": "L28"}, {"caller_nid": "agent_edit_setupagentediteventlisteners", "callee": "addEventListener", "source_file": "E:\\Livekit-CreativeNest\\Admin-Panel\\frontend\\assets\\scripts\\agent-edit.js", "source_location": "L30"}, {"caller_nid": "agent_edit_setupagentediteventlisteners", "callee": "getElementById", "source_file": "E:\\Livekit-CreativeNest\\Admin-Panel\\frontend\\assets\\scripts\\agent-edit.js", "source_location": "L33"}, {"caller_nid": "agent_edit_setupagentediteventlisteners", "callee": "addEventListener", "source_file": "E:\\Livekit-CreativeNest\\Admin-Panel\\frontend\\assets\\scripts\\agent-edit.js", "source_location": "L35"}, {"caller_nid": "agent_edit_setupagentediteventlisteners", "callee": "getElementById", "source_file": "E:\\Livekit-CreativeNest\\Admin-Panel\\frontend\\assets\\scripts\\agent-edit.js", "source_location": "L38"}, {"caller_nid": "agent_edit_setupagentediteventlisteners", "callee": "addEventListener", "source_file": "E:\\Livekit-CreativeNest\\Admin-Panel\\frontend\\assets\\scripts\\agent-edit.js", "source_location": "L40"}, {"caller_nid": "agent_edit_setupagentediteventlisteners", "callee": "addEventListener", "source_file": "E:\\Livekit-CreativeNest\\Admin-Panel\\frontend\\assets\\scripts\\agent-edit.js", "source_location": "L46"}, {"caller_nid": "agent_edit_setupagentediteventlisteners", "callee": "getElementById", "source_file": "E:\\Livekit-CreativeNest\\Admin-Panel\\frontend\\assets\\scripts\\agent-edit.js", "source_location": "L55"}, {"caller_nid": "agent_edit_setupagentediteventlisteners", "callee": "addEventListener", "source_file": "E:\\Livekit-CreativeNest\\Admin-Panel\\frontend\\assets\\scripts\\agent-edit.js", "source_location": "L57"}, {"caller_nid": "agent_edit_loadagentdetail", "callee": "showLoading", "source_file": "E:\\Livekit-CreativeNest\\Admin-Panel\\frontend\\assets\\scripts\\agent-edit.js", "source_location": "L66"}, {"caller_nid": "agent_edit_loadagentdetail", "callee": "showError", "source_file": "E:\\Livekit-CreativeNest\\Admin-Panel\\frontend\\assets\\scripts\\agent-edit.js", "source_location": "L67"}, {"caller_nid": "agent_edit_loadagentdetail", "callee": "getTools", "source_file": "E:\\Livekit-CreativeNest\\Admin-Panel\\frontend\\assets\\scripts\\agent-edit.js", "source_location": "L71"}, {"caller_nid": "agent_edit_loadagentdetail", "callee": "error", "source_file": "E:\\Livekit-CreativeNest\\Admin-Panel\\frontend\\assets\\scripts\\agent-edit.js", "source_location": "L78"}, {"caller_nid": "agent_edit_loadagentdetail", "callee": "showToast", "source_file": "E:\\Livekit-CreativeNest\\Admin-Panel\\frontend\\assets\\scripts\\agent-edit.js", "source_location": "L80"}, {"caller_nid": "agent_edit_loadagentdetail", "callee": "getVoices", "source_file": "E:\\Livekit-CreativeNest\\Admin-Panel\\frontend\\assets\\scripts\\agent-edit.js", "source_location": "L85"}, {"caller_nid": "agent_edit_loadagentdetail", "callee": "isArray", "source_file": "E:\\Livekit-CreativeNest\\Admin-Panel\\frontend\\assets\\scripts\\agent-edit.js", "source_location": "L86"}, {"caller_nid": "agent_edit_loadagentdetail", "callee": "error", "source_file": "E:\\Livekit-CreativeNest\\Admin-Panel\\frontend\\assets\\scripts\\agent-edit.js", "source_location": "L93"}, {"caller_nid": "agent_edit_loadagentdetail", "callee": "showToast", "source_file": "E:\\Livekit-CreativeNest\\Admin-Panel\\frontend\\assets\\scripts\\agent-edit.js", "source_location": "L95"}, {"caller_nid": "agent_edit_loadagentdetail", "callee": "showLoading", "source_file": "E:\\Livekit-CreativeNest\\Admin-Panel\\frontend\\assets\\scripts\\agent-edit.js", "source_location": "L101"}, {"caller_nid": "agent_edit_loadagentdetail", "callee": "toggleElement", "source_file": "E:\\Livekit-CreativeNest\\Admin-Panel\\frontend\\assets\\scripts\\agent-edit.js", "source_location": "L102"}, {"caller_nid": "agent_edit_loadagentdetail", "callee": "getElementById", "source_file": "E:\\Livekit-CreativeNest\\Admin-Panel\\frontend\\assets\\scripts\\agent-edit.js", "source_location": "L103"}, {"caller_nid": "agent_edit_loadagentdetail", "callee": "getAgent", "source_file": "E:\\Livekit-CreativeNest\\Admin-Panel\\frontend\\assets\\scripts\\agent-edit.js", "source_location": "L109"}, {"caller_nid": "agent_edit_loadagentdetail", "callee": "showLoading", "source_file": "E:\\Livekit-CreativeNest\\Admin-Panel\\frontend\\assets\\scripts\\agent-edit.js", "source_location": "L113"}, {"caller_nid": "agent_edit_loadagentdetail", "callee": "toggleElement", "source_file": "E:\\Livekit-CreativeNest\\Admin-Panel\\frontend\\assets\\scripts\\agent-edit.js", "source_location": "L114"}, {"caller_nid": "agent_edit_loadagentdetail", "callee": "error", "source_file": "E:\\Livekit-CreativeNest\\Admin-Panel\\frontend\\assets\\scripts\\agent-edit.js", "source_location": "L119"}, {"caller_nid": "agent_edit_loadagentdetail", "callee": "showLoading", "source_file": "E:\\Livekit-CreativeNest\\Admin-Panel\\frontend\\assets\\scripts\\agent-edit.js", "source_location": "L120"}, {"caller_nid": "agent_edit_loadagentdetail", "callee": "showError", "source_file": "E:\\Livekit-CreativeNest\\Admin-Panel\\frontend\\assets\\scripts\\agent-edit.js", "source_location": "L121"}, {"caller_nid": "agent_edit_loadagentdetail", "callee": "showToast", "source_file": "E:\\Livekit-CreativeNest\\Admin-Panel\\frontend\\assets\\scripts\\agent-edit.js", "source_location": "L122"}, {"caller_nid": "agent_edit_loadagentdetail", "callee": "error", "source_file": "E:\\Livekit-CreativeNest\\Admin-Panel\\frontend\\assets\\scripts\\agent-edit.js", "source_location": "L126"}, {"caller_nid": "agent_edit_populateagentform", "callee": "getElementById", "source_file": "E:\\Livekit-CreativeNest\\Admin-Panel\\frontend\\assets\\scripts\\agent-edit.js", "source_location": "L134"}, {"caller_nid": "agent_edit_populateagentform", "callee": "getElementById", "source_file": "E:\\Livekit-CreativeNest\\Admin-Panel\\frontend\\assets\\scripts\\agent-edit.js", "source_location": "L136"}, {"caller_nid": "agent_edit_populateagentform", "callee": "stringify", "source_file": "E:\\Livekit-CreativeNest\\Admin-Panel\\frontend\\assets\\scripts\\agent-edit.js", "source_location": "L140"}, {"caller_nid": "agent_edit_populateagentform", "callee": "getElementById", "source_file": "E:\\Livekit-CreativeNest\\Admin-Panel\\frontend\\assets\\scripts\\agent-edit.js", "source_location": "L152"}, {"caller_nid": "agent_edit_populateagentform", "callee": "getElementById", "source_file": "E:\\Livekit-CreativeNest\\Admin-Panel\\frontend\\assets\\scripts\\agent-edit.js", "source_location": "L153"}, {"caller_nid": "agent_edit_populateagentform", "callee": "getElementById", "source_file": "E:\\Livekit-CreativeNest\\Admin-Panel\\frontend\\assets\\scripts\\agent-edit.js", "source_location": "L154"}, {"caller_nid": "agent_edit_populateagentform", "callee": "getElementById", "source_file": "E:\\Livekit-CreativeNest\\Admin-Panel\\frontend\\assets\\scripts\\agent-edit.js", "source_location": "L155"}, {"caller_nid": "agent_edit_populateagentform", "callee": "getElementById", "source_file": "E:\\Livekit-CreativeNest\\Admin-Panel\\frontend\\assets\\scripts\\agent-edit.js", "source_location": "L167"}, {"caller_nid": "agent_edit_populateagentform", "callee": "getElementById", "source_file": "E:\\Livekit-CreativeNest\\Admin-Panel\\frontend\\assets\\scripts\\agent-edit.js", "source_location": "L171"}, {"caller_nid": "agent_edit_populateagentform", "callee": "getElementById", "source_file": "E:\\Livekit-CreativeNest\\Admin-Panel\\frontend\\assets\\scripts\\agent-edit.js", "source_location": "L174"}, {"caller_nid": "agent_edit_populateagentform", "callee": "getElementById", "source_file": "E:\\Livekit-CreativeNest\\Admin-Panel\\frontend\\assets\\scripts\\agent-edit.js", "source_location": "L177"}, {"caller_nid": "agent_edit_populateagentform", "callee": "getElementById", "source_file": "E:\\Livekit-CreativeNest\\Admin-Panel\\frontend\\assets\\scripts\\agent-edit.js", "source_location": "L180"}, {"caller_nid": "agent_edit_populateagentform", "callee": "getElementById", "source_file": "E:\\Livekit-CreativeNest\\Admin-Panel\\frontend\\assets\\scripts\\agent-edit.js", "source_location": "L181"}, {"caller_nid": "agent_edit_populateagentform", "callee": "getElementById", "source_file": "E:\\Livekit-CreativeNest\\Admin-Panel\\frontend\\assets\\scripts\\agent-edit.js", "source_location": "L182"}, {"caller_nid": "agent_edit_populateagentform", "callee": "getElementById", "source_file": "E:\\Livekit-CreativeNest\\Admin-Panel\\frontend\\assets\\scripts\\agent-edit.js", "source_location": "L185"}, {"caller_nid": "agent_edit_populateagentform", "callee": "getElementById", "source_file": "E:\\Livekit-CreativeNest\\Admin-Panel\\frontend\\assets\\scripts\\agent-edit.js", "source_location": "L186"}, {"caller_nid": "agent_edit_populateagentform", "callee": "getElementById", "source_file": "E:\\Livekit-CreativeNest\\Admin-Panel\\frontend\\assets\\scripts\\agent-edit.js", "source_location": "L187"}, {"caller_nid": "agent_edit_populateagentform", "callee": "getElementById", "source_file": "E:\\Livekit-CreativeNest\\Admin-Panel\\frontend\\assets\\scripts\\agent-edit.js", "source_location": "L189"}, {"caller_nid": "agent_edit_populateagentform", "callee": "getElementById", "source_file": "E:\\Livekit-CreativeNest\\Admin-Panel\\frontend\\assets\\scripts\\agent-edit.js", "source_location": "L190"}, {"caller_nid": "agent_edit_populateagentform", "callee": "join", "source_file": "E:\\Livekit-CreativeNest\\Admin-Panel\\frontend\\assets\\scripts\\agent-edit.js", "source_location": "L190"}, {"caller_nid": "agent_edit_populateagentform", "callee": "getElementById", "source_file": "E:\\Livekit-CreativeNest\\Admin-Panel\\frontend\\assets\\scripts\\agent-edit.js", "source_location": "L191"}, {"caller_nid": "agent_edit_populateagentform", "callee": "join", "source_file": "E:\\Livekit-CreativeNest\\Admin-Panel\\frontend\\assets\\scripts\\agent-edit.js", "source_location": "L191"}, {"caller_nid": "agent_edit_populateagentform", "callee": "getElementById", "source_file": "E:\\Livekit-CreativeNest\\Admin-Panel\\frontend\\assets\\scripts\\agent-edit.js", "source_location": "L195"}, {"caller_nid": "agent_edit_populateagentform", "callee": "getElementById", "source_file": "E:\\Livekit-CreativeNest\\Admin-Panel\\frontend\\assets\\scripts\\agent-edit.js", "source_location": "L196"}, {"caller_nid": "agent_edit_populateagentform", "callee": "getElementById", "source_file": "E:\\Livekit-CreativeNest\\Admin-Panel\\frontend\\assets\\scripts\\agent-edit.js", "source_location": "L197"}, {"caller_nid": "agent_edit_populateagentform", "callee": "getElementById", "source_file": "E:\\Livekit-CreativeNest\\Admin-Panel\\frontend\\assets\\scripts\\agent-edit.js", "source_location": "L198"}, {"caller_nid": "agent_edit_populateagentform", "callee": "keys", "source_file": "E:\\Livekit-CreativeNest\\Admin-Panel\\frontend\\assets\\scripts\\agent-edit.js", "source_location": "L201"}, {"caller_nid": "agent_edit_handleagentformsubmit", "callee": "preventDefault", "source_file": "E:\\Livekit-CreativeNest\\Admin-Panel\\frontend\\assets\\scripts\\agent-edit.js", "source_location": "L206"}, {"caller_nid": "agent_edit_handleagentformsubmit", "callee": "trim", "source_file": "E:\\Livekit-CreativeNest\\Admin-Panel\\frontend\\assets\\scripts\\agent-edit.js", "source_location": "L208"}, {"caller_nid": "agent_edit_handleagentformsubmit", "callee": "getElementById", "source_file": "E:\\Livekit-CreativeNest\\Admin-Panel\\frontend\\assets\\scripts\\agent-edit.js", "source_location": "L208"}, {"caller_nid": "agent_edit_handleagentformsubmit", "callee": "showToast", "source_file": "E:\\Livekit-CreativeNest\\Admin-Panel\\frontend\\assets\\scripts\\agent-edit.js", "source_location": "L210"}, {"caller_nid": "agent_edit_handleagentformsubmit", "callee": "trim", "source_file": "E:\\Livekit-CreativeNest\\Admin-Panel\\frontend\\assets\\scripts\\agent-edit.js", "source_location": "L215"}, {"caller_nid": "agent_edit_handleagentformsubmit", "callee": "getElementById", "source_file": "E:\\Livekit-CreativeNest\\Admin-Panel\\frontend\\assets\\scripts\\agent-edit.js", "source_location": "L215"}, {"caller_nid": "agent_edit_handleagentformsubmit", "callee": "parse", "source_file": "E:\\Livekit-CreativeNest\\Admin-Panel\\frontend\\assets\\scripts\\agent-edit.js", "source_location": "L218"}, {"caller_nid": "agent_edit_handleagentformsubmit", "callee": "error", "source_file": "E:\\Livekit-CreativeNest\\Admin-Panel\\frontend\\assets\\scripts\\agent-edit.js", "source_location": "L220"}, {"caller_nid": "agent_edit_handleagentformsubmit", "callee": "showToast", "source_file": "E:\\Livekit-CreativeNest\\Admin-Panel\\frontend\\assets\\scripts\\agent-edit.js", "source_location": "L221"}, {"caller_nid": "agent_edit_handleagentformsubmit", "callee": "trim", "source_file": "E:\\Livekit-CreativeNest\\Admin-Panel\\frontend\\assets\\scripts\\agent-edit.js", "source_location": "L229"}, {"caller_nid": "agent_edit_handleagentformsubmit", "callee": "getElementById", "source_file": "E:\\Livekit-CreativeNest\\Admin-Panel\\frontend\\assets\\scripts\\agent-edit.js", "source_location": "L229"}, {"caller_nid": "agent_edit_handleagentformsubmit", "callee": "trim", "source_file": "E:\\Livekit-CreativeNest\\Admin-Panel\\frontend\\assets\\scripts\\agent-edit.js", "source_location": "L230"}, {"caller_nid": "agent_edit_handleagentformsubmit", "callee": "getElementById", "source_file": "E:\\Livekit-CreativeNest\\Admin-Panel\\frontend\\assets\\scripts\\agent-edit.js", "source_location": "L230"}, {"caller_nid": "agent_edit_handleagentformsubmit", "callee": "getElementById", "source_file": "E:\\Livekit-CreativeNest\\Admin-Panel\\frontend\\assets\\scripts\\agent-edit.js", "source_location": "L231"}, {"caller_nid": "agent_edit_handleagentformsubmit", "callee": "getElementById", "source_file": "E:\\Livekit-CreativeNest\\Admin-Panel\\frontend\\assets\\scripts\\agent-edit.js", "source_location": "L232"}, {"caller_nid": "agent_edit_handleagentformsubmit", "callee": "trim", "source_file": "E:\\Livekit-CreativeNest\\Admin-Panel\\frontend\\assets\\scripts\\agent-edit.js", "source_location": "L233"}, {"caller_nid": "agent_edit_handleagentformsubmit", "callee": "trim", "source_file": "E:\\Livekit-CreativeNest\\Admin-Panel\\frontend\\assets\\scripts\\agent-edit.js", "source_location": "L234"}, {"caller_nid": "agent_edit_handleagentformsubmit", "callee": "getElementById", "source_file": "E:\\Livekit-CreativeNest\\Admin-Panel\\frontend\\assets\\scripts\\agent-edit.js", "source_location": "L249"}, {"caller_nid": "agent_edit_handleagentformsubmit", "callee": "getElementById", "source_file": "E:\\Livekit-CreativeNest\\Admin-Panel\\frontend\\assets\\scripts\\agent-edit.js", "source_location": "L251"}, {"caller_nid": "agent_edit_handleagentformsubmit", "callee": "getElementById", "source_file": "E:\\Livekit-CreativeNest\\Admin-Panel\\frontend\\assets\\scripts\\agent-edit.js", "source_location": "L252"}, {"caller_nid": "agent_edit_handleagentformsubmit", "callee": "getElementById", "source_file": "E:\\Livekit-CreativeNest\\Admin-Panel\\frontend\\assets\\scripts\\agent-edit.js", "source_location": "L253"}, {"caller_nid": "agent_edit_handleagentformsubmit", "callee": "getElementById", "source_file": "E:\\Livekit-CreativeNest\\Admin-Panel\\frontend\\assets\\scripts\\agent-edit.js", "source_location": "L256"}, {"caller_nid": "agent_edit_handleagentformsubmit", "callee": "getElementById", "source_file": "E:\\Livekit-CreativeNest\\Admin-Panel\\frontend\\assets\\scripts\\agent-edit.js", "source_location": "L257"}, {"caller_nid": "agent_edit_handleagentformsubmit", "callee": "getElementById", "source_file": "E:\\Livekit-CreativeNest\\Admin-Panel\\frontend\\assets\\scripts\\agent-edit.js", "source_location": "L258"}, {"caller_nid": "agent_edit_handleagentformsubmit", "callee": "getElementById", "source_file": "E:\\Livekit-CreativeNest\\Admin-Panel\\frontend\\assets\\scripts\\agent-edit.js", "source_location": "L261"}, {"caller_nid": "agent_edit_handleagentformsubmit", "callee": "getElementById", "source_file": "E:\\Livekit-CreativeNest\\Admin-Panel\\frontend\\assets\\scripts\\agent-edit.js", "source_location": "L264"}, {"caller_nid": "agent_edit_handleagentformsubmit", "callee": "filter", "source_file": "E:\\Livekit-CreativeNest\\Admin-Panel\\frontend\\assets\\scripts\\agent-edit.js", "source_location": "L267"}, {"caller_nid": "agent_edit_handleagentformsubmit", "callee": "map", "source_file": "E:\\Livekit-CreativeNest\\Admin-Panel\\frontend\\assets\\scripts\\agent-edit.js", "source_location": "L267"}, {"caller_nid": "agent_edit_handleagentformsubmit", "callee": "split", "source_file": "E:\\Livekit-CreativeNest\\Admin-Panel\\frontend\\assets\\scripts\\agent-edit.js", "source_location": "L267"}, {"caller_nid": "agent_edit_handleagentformsubmit", "callee": "getElementById", "source_file": "E:\\Livekit-CreativeNest\\Admin-Panel\\frontend\\assets\\scripts\\agent-edit.js", "source_location": "L267"}, {"caller_nid": "agent_edit_handleagentformsubmit", "callee": "getElementById", "source_file": "E:\\Livekit-CreativeNest\\Admin-Panel\\frontend\\assets\\scripts\\agent-edit.js", "source_location": "L270"}, {"caller_nid": "agent_edit_handleagentformsubmit", "callee": "filter", "source_file": "E:\\Livekit-CreativeNest\\Admin-Panel\\frontend\\assets\\scripts\\agent-edit.js", "source_location": "L272"}, {"caller_nid": "agent_edit_handleagentformsubmit", "callee": "map", "source_file": "E:\\Livekit-CreativeNest\\Admin-Panel\\frontend\\assets\\scripts\\agent-edit.js", "source_location": "L272"}, {"caller_nid": "agent_edit_handleagentformsubmit", "callee": "split", "source_file": "E:\\Livekit-CreativeNest\\Admin-Panel\\frontend\\assets\\scripts\\agent-edit.js", "source_location": "L272"}, {"caller_nid": "agent_edit_handleagentformsubmit", "callee": "getElementById", "source_file": "E:\\Livekit-CreativeNest\\Admin-Panel\\frontend\\assets\\scripts\\agent-edit.js", "source_location": "L272"}, {"caller_nid": "agent_edit_handleagentformsubmit", "callee": "getElementById", "source_file": "E:\\Livekit-CreativeNest\\Admin-Panel\\frontend\\assets\\scripts\\agent-edit.js", "source_location": "L277"}, {"caller_nid": "agent_edit_handleagentformsubmit", "callee": "getElementById", "source_file": "E:\\Livekit-CreativeNest\\Admin-Panel\\frontend\\assets\\scripts\\agent-edit.js", "source_location": "L278"}, {"caller_nid": "agent_edit_handleagentformsubmit", "callee": "(() => {\r\n            const selected = Array.from(document.querySelectorAll('input[name=\"session-tools\"]:checked'))\r\n                .map(el => el.value);\r\n            const toolsConfig = {};\r\n            selected.forEach(id => {\r\n                if (availableTools && availableTools[id]) {\r\n                    toolsConfig[id] = availableTools[id];\r\n                }\r\n            });\r\n            return toolsConfig;\r\n        })", "source_file": "E:\\Livekit-CreativeNest\\Admin-Panel\\frontend\\assets\\scripts\\agent-edit.js", "source_location": "L280"}, {"caller_nid": "agent_edit_handleagentformsubmit", "callee": "getElementById", "source_file": "E:\\Livekit-CreativeNest\\Admin-Panel\\frontend\\assets\\scripts\\agent-edit.js", "source_location": "L291"}, {"caller_nid": "agent_edit_handleagentformsubmit", "callee": "getElementById", "source_file": "E:\\Livekit-CreativeNest\\Admin-Panel\\frontend\\assets\\scripts\\agent-edit.js", "source_location": "L293"}, {"caller_nid": "agent_edit_handleagentformsubmit", "callee": "keys", "source_file": "E:\\Livekit-CreativeNest\\Admin-Panel\\frontend\\assets\\scripts\\agent-edit.js", "source_location": "L303"}, {"caller_nid": "agent_edit_handleagentformsubmit", "callee": "querySelector", "source_file": "E:\\Livekit-CreativeNest\\Admin-Panel\\frontend\\assets\\scripts\\agent-edit.js", "source_location": "L307"}, {"caller_nid": "agent_edit_handleagentformsubmit", "callee": "updateAgent", "source_file": "E:\\Livekit-CreativeNest\\Admin-Panel\\frontend\\assets\\scripts\\agent-edit.js", "source_location": "L316"}, {"caller_nid": "agent_edit_handleagentformsubmit", "callee": "createAgent", "source_file": "E:\\Livekit-CreativeNest\\Admin-Panel\\frontend\\assets\\scripts\\agent-edit.js", "source_location": "L318"}, {"caller_nid": "agent_edit_handleagentformsubmit", "callee": "showToast", "source_file": "E:\\Livekit-CreativeNest\\Admin-Panel\\frontend\\assets\\scripts\\agent-edit.js", "source_location": "L324"}, {"caller_nid": "agent_edit_handleagentformsubmit", "callee": "setTimeout", "source_file": "E:\\Livekit-CreativeNest\\Admin-Panel\\frontend\\assets\\scripts\\agent-edit.js", "source_location": "L329"}, {"caller_nid": "agent_edit_handleagentformsubmit", "callee": "error", "source_file": "E:\\Livekit-CreativeNest\\Admin-Panel\\frontend\\assets\\scripts\\agent-edit.js", "source_location": "L336"}, {"caller_nid": "agent_edit_handleagentformsubmit", "callee": "showToast", "source_file": "E:\\Livekit-CreativeNest\\Admin-Panel\\frontend\\assets\\scripts\\agent-edit.js", "source_location": "L337"}, {"caller_nid": "agent_edit_handleagentdelete", "callee": "confirm", "source_file": "E:\\Livekit-CreativeNest\\Admin-Panel\\frontend\\assets\\scripts\\agent-edit.js", "source_location": "L346"}, {"caller_nid": "agent_edit_handleagentdelete", "callee": "getElementById", "source_file": "E:\\Livekit-CreativeNest\\Admin-Panel\\frontend\\assets\\scripts\\agent-edit.js", "source_location": "L350"}, {"caller_nid": "agent_edit_handleagentdelete", "callee": "deleteAgent", "source_file": "E:\\Livekit-CreativeNest\\Admin-Panel\\frontend\\assets\\scripts\\agent-edit.js", "source_location": "L355"}, {"caller_nid": "agent_edit_handleagentdelete", "callee": "showToast", "source_file": "E:\\Livekit-CreativeNest\\Admin-Panel\\frontend\\assets\\scripts\\agent-edit.js", "source_location": "L357"}, {"caller_nid": "agent_edit_handleagentdelete", "callee": "setTimeout", "source_file": "E:\\Livekit-CreativeNest\\Admin-Panel\\frontend\\assets\\scripts\\agent-edit.js", "source_location": "L358"}, {"caller_nid": "agent_edit_handleagentdelete", "callee": "error", "source_file": "E:\\Livekit-CreativeNest\\Admin-Panel\\frontend\\assets\\scripts\\agent-edit.js", "source_location": "L365"}, {"caller_nid": "agent_edit_handleagentdelete", "callee": "showToast", "source_file": "E:\\Livekit-CreativeNest\\Admin-Panel\\frontend\\assets\\scripts\\agent-edit.js", "source_location": "L366"}, {"caller_nid": "agent_edit_rendertoolsselector", "callee": "getElementById", "source_file": "E:\\Livekit-CreativeNest\\Admin-Panel\\frontend\\assets\\scripts\\agent-edit.js", "source_location": "L373"}, {"caller_nid": "agent_edit_rendertoolsselector", "callee": "keys", "source_file": "E:\\Livekit-CreativeNest\\Admin-Panel\\frontend\\assets\\scripts\\agent-edit.js", "source_location": "L376"}, {"caller_nid": "agent_edit_rendertoolsselector", "callee": "forEach", "source_file": "E:\\Livekit-CreativeNest\\Admin-Panel\\frontend\\assets\\scripts\\agent-edit.js", "source_location": "L384"}, {"caller_nid": "agent_edit_rendertoolsselector", "callee": "querySelectorAll", "source_file": "E:\\Livekit-CreativeNest\\Admin-Panel\\frontend\\assets\\scripts\\agent-edit.js", "source_location": "L422"}, {"caller_nid": "agent_edit_rendertoolsselector", "callee": "forEach", "source_file": "E:\\Livekit-CreativeNest\\Admin-Panel\\frontend\\assets\\scripts\\agent-edit.js", "source_location": "L423"}, {"caller_nid": "agent_edit_toggletoolsdropdown", "callee": "getElementById", "source_file": "E:\\Livekit-CreativeNest\\Admin-Panel\\frontend\\assets\\scripts\\agent-edit.js", "source_location": "L431"}, {"caller_nid": "agent_edit_toggletoolsdropdown", "callee": "toggle", "source_file": "E:\\Livekit-CreativeNest\\Admin-Panel\\frontend\\assets\\scripts\\agent-edit.js", "source_location": "L440"}, {"caller_nid": "agent_edit_updatetoolsdropdownsummary", "callee": "getElementById", "source_file": "E:\\Livekit-CreativeNest\\Admin-Panel\\frontend\\assets\\scripts\\agent-edit.js", "source_location": "L444"}, {"caller_nid": "agent_edit_updatetoolsdropdownsummary", "callee": "getElementById", "source_file": "E:\\Livekit-CreativeNest\\Admin-Panel\\frontend\\assets\\scripts\\agent-edit.js", "source_location": "L445"}, {"caller_nid": "agent_edit_updatetoolsdropdownsummary", "callee": "map", "source_file": "E:\\Livekit-CreativeNest\\Admin-Panel\\frontend\\assets\\scripts\\agent-edit.js", "source_location": "L446"}, {"caller_nid": "agent_edit_updatetoolsdropdownsummary", "callee": "from", "source_file": "E:\\Livekit-CreativeNest\\Admin-Panel\\frontend\\assets\\scripts\\agent-edit.js", "source_location": "L446"}, {"caller_nid": "agent_edit_updatetoolsdropdownsummary", "callee": "querySelectorAll", "source_file": "E:\\Livekit-CreativeNest\\Admin-Panel\\frontend\\assets\\scripts\\agent-edit.js", "source_location": "L446"}, {"caller_nid": "agent_edit_updatetoolsdropdownsummary", "callee": "map", "source_file": "E:\\Livekit-CreativeNest\\Admin-Panel\\frontend\\assets\\scripts\\agent-edit.js", "source_location": "L457"}, {"caller_nid": "agent_edit_updatetoolsdropdownsummary", "callee": "join", "source_file": "E:\\Livekit-CreativeNest\\Admin-Panel\\frontend\\assets\\scripts\\agent-edit.js", "source_location": "L458"}, {"caller_nid": "agent_edit_updatetoolsdropdownsummary", "callee": "slice", "source_file": "E:\\Livekit-CreativeNest\\Admin-Panel\\frontend\\assets\\scripts\\agent-edit.js", "source_location": "L458"}, {"caller_nid": "agent_edit_getagentidfromurl", "callee": "get", "source_file": "E:\\Livekit-CreativeNest\\Admin-Panel\\frontend\\assets\\scripts\\agent-edit.js", "source_location": "L472"}, {"caller_nid": "agent_edit_populatettsprovideroptions", "callee": "getElementById", "source_file": "E:\\Livekit-CreativeNest\\Admin-Panel\\frontend\\assets\\scripts\\agent-edit.js", "source_location": "L476"}, {"caller_nid": "agent_edit_populatettsprovideroptions", "callee": "from", "source_file": "E:\\Livekit-CreativeNest\\Admin-Panel\\frontend\\assets\\scripts\\agent-edit.js", "source_location": "L479"}, {"caller_nid": "agent_edit_populatettsprovideroptions", "callee": "filter", "source_file": "E:\\Livekit-CreativeNest\\Admin-Panel\\frontend\\assets\\scripts\\agent-edit.js", "source_location": "L480"}, {"caller_nid": "agent_edit_populatettsprovideroptions", "callee": "map", "source_file": "E:\\Livekit-CreativeNest\\Admin-Panel\\frontend\\assets\\scripts\\agent-edit.js", "source_location": "L480"}, {"caller_nid": "agent_edit_populatettsprovideroptions", "callee": "forEach", "source_file": "E:\\Livekit-CreativeNest\\Admin-Panel\\frontend\\assets\\scripts\\agent-edit.js", "source_location": "L487"}, {"caller_nid": "agent_edit_populatettsvoiceoptions", "callee": "getElementById", "source_file": "E:\\Livekit-CreativeNest\\Admin-Panel\\frontend\\assets\\scripts\\agent-edit.js", "source_location": "L496"}, {"caller_nid": "agent_edit_populatettsvoiceoptions", "callee": "forEach", "source_file": "E:\\Livekit-CreativeNest\\Admin-Panel\\frontend\\assets\\scripts\\agent-edit.js", "source_location": "L505"}, {"caller_nid": "agent_edit_populatettsvoiceoptions", "callee": "filter", "source_file": "E:\\Livekit-CreativeNest\\Admin-Panel\\frontend\\assets\\scripts\\agent-edit.js", "source_location": "L505"}]}